pts_fault_injection/CANFWupdate.py
pts_fault_injection/__init__.py
pts_fault_injection/cmb_box.py
pts_fault_injection/fib_controller.py
pts_fault_injection/load_box.py
pts_fault_injection/dbc/hilcan.dbc
pts_fault_injection-0.1.2.dist-info/LICENSE.txt
pts_fault_injection-0.1.2.dist-info/METADATA
pts_fault_injection-0.1.2.dist-info/WHEEL
pts_fault_injection-0.1.2.dist-info/top_level.txt
pts_fault_injection-0.1.2.dist-info/RECORD
