Metadata-Version: 2.1
Name: pts-fault-injection
Version: 0.1.2
Summary: Fault Injection box Diagnostics package Diagnostic Package
Home-page: https://gitlab.com/pass-testing-solutions/pts-fault-injection-box
Author: Pass testing Solutions GmbH
Author-email: shuparna@pass-testing.de
License: MIT
Platform: UNKNOWN
Classifier: License :: OSI Approved :: MIT License
Classifier: Programming Language :: Python :: 3
Classifier: Programming Language :: Python :: 3.9
License-File: LICENSE.txt
Requires-Dist: python-can (>=4.0.0)
Requires-Dist: cantools (>=37.0.7)
Requires-Dist: uptime (==3.0.1)
